clts_pcp/__init__.py
clts_pcp/clts.py
clts_pcp/setup.py
clts_pcp/testlistts.py
clts_pcp/lts.egg-info/PKG-INFO
clts_pcp/lts.egg-info/SOURCES.txt
clts_pcp/lts.egg-info/dependency_links.txt
clts_pcp/lts.egg-info/requires.txt
clts_pcp/lts.egg-info/top_level.txt
clts_pcp-1.0.3.dist-info/METADATA
clts_pcp-1.0.3.dist-info/WHEEL
clts_pcp-1.0.3.dist-info/licenses/LICENSE
clts_pcp-1.0.3.dist-info/RECORD
