Metadata-Version: 2.4
Name: clts_pcp
Version: 1.0.3
Summary: Collecting and listing tasks and timestamps
Project-URL: Homepage, https://github.com/pedroccpimenta/clts_pcp
Project-URL: Issues, https://github.com/pedroccpimenta/clts_pcp/issues
Author-email: Pedro Pimenta <pedroccpimenta@gmail.com>
License-File: LICENSE
Classifier: License :: OSI Approved :: MIT License
Classifier: Operating System :: OS Independent
Classifier: Programming Language :: Python :: 3
Requires-Python: >=3.6
